genesis_flow-1.0.9.dist-info/licenses/LICENSE.txt
mlflow/__init__.py
mlflow/__main__.py
mlflow/cli.py
mlflow/client.py
mlflow/db.py
mlflow/environment_variables.py
mlflow/exceptions.py
mlflow/experiments.py
mlflow/mismatch.py
mlflow/ml_package_versions.py
mlflow/py.typed
mlflow/runs.py
mlflow/version.py
mlflow/ag2/__init__.py
mlflow/ag2/ag2_logger.py
mlflow/anthropic/__init__.py
mlflow/anthropic/autolog.py
mlflow/anthropic/chat.py
mlflow/artifacts/__init__.py
mlflow/autogen/__init__.py
mlflow/autogen/chat.py
mlflow/azure/__init__.py
mlflow/azure/auth_handler.py
mlflow/azure/client.py
mlflow/azure/config.py
mlflow/azure/connection_factory.py
mlflow/azure/exceptions.py
mlflow/azure/stores.py
mlflow/azure/utils.py
mlflow/bedrock/__init__.py
mlflow/bedrock/_autolog.py
mlflow/bedrock/chat.py
mlflow/bedrock/stream.py
mlflow/bedrock/utils.py
mlflow/config/__init__.py
mlflow/crewai/__init__.py
mlflow/crewai/autolog.py
mlflow/crewai/chat.py
mlflow/data/__init__.py
mlflow/data/artifact_dataset_sources.py
mlflow/data/code_dataset_source.py
mlflow/data/dataset.py
mlflow/data/dataset_registry.py
mlflow/data/dataset_source.py
mlflow/data/dataset_source_registry.py
mlflow/data/delta_dataset_source.py
mlflow/data/digest_utils.py
mlflow/data/evaluation_dataset.py
mlflow/data/filesystem_dataset_source.py
mlflow/data/http_dataset_source.py
mlflow/data/huggingface_dataset.py
mlflow/data/huggingface_dataset_source.py
mlflow/data/meta_dataset.py
mlflow/data/numpy_dataset.py
mlflow/data/pandas_dataset.py
mlflow/data/polars_dataset.py
mlflow/data/pyfunc_dataset_mixin.py
mlflow/data/schema.py
mlflow/data/sources.py
mlflow/data/spark_dataset.py
mlflow/data/spark_dataset_source.py
mlflow/data/spark_delta_utils.py
mlflow/data/tensorflow_dataset.py
mlflow/data/uc_volume_dataset_source.py
mlflow/dspy/__init__.py
mlflow/dspy/autolog.py
mlflow/dspy/callback.py
mlflow/dspy/constant.py
mlflow/dspy/load.py
mlflow/dspy/save.py
mlflow/dspy/util.py
mlflow/dspy/wrapper.py
mlflow/entities/__init__.py
mlflow/entities/_mlflow_object.py
genesis_flow-1.0.9.dist-info/METADATA
genesis_flow-1.0.9.dist-info/WHEEL
genesis_flow-1.0.9.dist-info/entry_points.txt
genesis_flow-1.0.9.dist-info/top_level.txt
genesis_flow-1.0.9.dist-info/RECORD
