Metadata-Version: 2.4
Name: genesis-flow
Version: 1.0.9
Summary: Genesis-Flow: MLflow v3.1.4 compatible fork for Genesis platform
Maintainer-email: Databricks <mlflow-oss-maintainers@googlegroups.com>
License: Copyright 2018 Databricks, Inc.  All rights reserved.
Project-URL: homepage, https://github.com/autonomize/genesis-flow
Project-URL: issues, https://github.com/autonomize/genesis-flow/issues
Project-URL: documentation, https://github.com/autonomize/genesis-flow/blob/main/README.md
Project-URL: repository, https://github.com/autonomize/genesis-flow
Keywords: mlflow,ai,databricks
Classifier: Development Status :: 5 - Production/Stable
Classifier: Intended Audience :: Developers
Classifier: Intended Audience :: End Users/Desktop
Classifier: Intended Audience :: Science/Research
Classifier: Intended Audience :: Information Technology
Classifier: Topic :: Scientific/Engineering :: Artificial Intelligence
Classifier: Topic :: Software Development :: Libraries :: Python Modules
Classifier: License :: OSI Approved :: Apache Software License
Classifier: Operating System :: OS Independent
Classifier: Programming Language :: Python :: 3.9
Requires-Python: >=3.9
License-File: LICENSE.txt
Requires-Dist: Flask<4,>=2.3.3
Requires-Dist: werkzeug<4,>=3.0.1
Requires-Dist: alembic!=1.10.0,<2
Requires-Dist: cachetools<7,>=5.0.0
Requires-Dist: click<9,>=7.0
Requires-Dist: cloudpickle<4
Requires-Dist: gunicorn<24; platform_system != "Windows"
Requires-Dist: importlib_metadata!=4.7.0,<9,>=3.7.0
Requires-Dist: packaging<26
Requires-Dist: protobuf<7,>=4.25.0
Requires-Dist: pydantic<3,>=1.10.8
Requires-Dist: pyyaml<7,>=6.0.1
Requires-Dist: requests<3,>=2.17.3
Requires-Dist: sqlalchemy<3,>=1.4.0
Requires-Dist: sqlparse<1,>=0.4.0
Requires-Dist: typing-extensions<5,>=4.0.0
Requires-Dist: waitress<4; platform_system == "Windows"
Requires-Dist: jinja2>=3.1.6
Requires-Dist: cryptography>=41.0.6
Requires-Dist: numpy<3,>=1.24.0
Requires-Dist: pandas<3,>=2.1.4
Requires-Dist: pyarrow==21.0.0
Requires-Dist: scikit-learn<2
Requires-Dist: scipy<2
Provides-Extra: pytorch
Requires-Dist: torch>=2.0.0; extra == "pytorch"
Requires-Dist: torchvision>=0.15.0; extra == "pytorch"
Provides-Extra: transformers
Requires-Dist: transformers>=4.36.0; extra == "transformers"
Requires-Dist: sentencepiece>=0.1.99; extra == "transformers"
Provides-Extra: llm
Requires-Dist: openai>=1.0.0; extra == "llm"
Requires-Dist: langchain<=0.3.25,>=0.1.0; extra == "llm"
Provides-Extra: cloud
Requires-Dist: boto3<2.0.0,>=1.34.0; extra == "cloud"
Requires-Dist: azure-storage-blob<13.0.0,>=12.19.0; extra == "cloud"
Requires-Dist: google-cloud-storage<3.0.0,>=2.10.0; extra == "cloud"
Provides-Extra: all
Requires-Dist: genesis-flow[cloud,llm,pytorch,transformers]; extra == "all"
Provides-Extra: databricks
Requires-Dist: databricks-sdk<1,>=0.20.0; extra == "databricks"
Requires-Dist: azure-storage-file-datalake>12; extra == "databricks"
Requires-Dist: boto3>1; extra == "databricks"
Requires-Dist: botocore; extra == "databricks"
Requires-Dist: databricks-agents<2.0,>=1.0.0; extra == "databricks"
Provides-Extra: mlserver
Requires-Dist: mlserver!=1.3.1,<2.0.0,>=1.2.0; extra == "mlserver"
Requires-Dist: mlserver-mlflow!=1.3.1,<2.0.0,>=1.2.0; extra == "mlserver"
Provides-Extra: gateway
Requires-Dist: fastapi<1; extra == "gateway"
Requires-Dist: uvicorn[standard]<1; extra == "gateway"
Requires-Dist: watchfiles<2; extra == "gateway"
Requires-Dist: aiohttp<4; extra == "gateway"
Requires-Dist: boto3<2,>=1.28.56; extra == "gateway"
Requires-Dist: tiktoken<1; extra == "gateway"
Requires-Dist: slowapi<1,>=0.1.9; extra == "gateway"
Provides-Extra: genai
Requires-Dist: fastapi<1; extra == "genai"
Requires-Dist: uvicorn[standard]<1; extra == "genai"
Requires-Dist: watchfiles<2; extra == "genai"
Requires-Dist: aiohttp<4; extra == "genai"
Requires-Dist: boto3<2,>=1.28.56; extra == "genai"
Requires-Dist: tiktoken<1; extra == "genai"
Requires-Dist: slowapi<1,>=0.1.9; extra == "genai"
Provides-Extra: sqlserver
Requires-Dist: mlflow-dbstore; extra == "sqlserver"
Provides-Extra: aliyun-oss
Requires-Dist: aliyunstoreplugin; extra == "aliyun-oss"
Provides-Extra: xethub
Requires-Dist: mlflow-xethub; extra == "xethub"
Provides-Extra: jfrog
Requires-Dist: mlflow-jfrog-plugin; extra == "jfrog"
Provides-Extra: langchain
Requires-Dist: langchain<=0.3.25,>=0.1.0; extra == "langchain"
Provides-Extra: auth
Requires-Dist: Flask-WTF<2; extra == "auth"
Provides-Extra: extras
Requires-Dist: prometheus-flask-exporter; extra == "extras"
Requires-Dist: docker<8,>=4.0.0; extra == "extras"
Requires-Dist: matplotlib<4; extra == "extras"
Requires-Dist: fastapi<1; extra == "extras"
Requires-Dist: uvicorn<1; extra == "extras"
Dynamic: license-file
